python_ted-0.0.6.dist-info/dependency_links.txt
python_ted-0.0.6.dist-info/DESCRIPTION.rst
python_ted-0.0.6.dist-info/METADATA
python_ted-0.0.6.dist-info/pydist.json
python_ted-0.0.6.dist-info/RECORD
python_ted-0.0.6.dist-info/top_level.txt
python_ted-0.0.6.dist-info/WHEEL
ted/__init__.py
ted/aspx_session.py
ted/client.py
ted/course.py
