Metadata-Version: 2.0
Name: python-ted
Version: 0.0.6
Summary: Python library for the University of Edinburgh's T@Ed Timetabling Service
Home-page: https://github.com/jeffbr13/python-ted
Author: Ben Jeffrey
Author-email: mail@benjeffrey.com
License: MPL 2.0
Keywords: calendar edinburgh timetable
Platform: UNKNOWN
Classifier: Development Status :: 3 - Alpha
Classifier: Intended Audience :: Developers
Classifier: Topic :: Software Development :: Libraries
Classifier: Topic :: Internet
Classifier: Topic :: Internet :: WWW/HTTP :: Indexing/Search
Classifier: Topic :: Internet :: WWW/HTTP :: Dynamic Content :: News/Diary
Classifier: License :: OSI Approved :: Mozilla Public License 2.0 (MPL 2.0)
Classifier: Programming Language :: Python :: 2
Classifier: Programming Language :: Python :: 2.6
Classifier: Programming Language :: Python :: 2.7
Classifier: Programming Language :: Python :: 3
Classifier: Programming Language :: Python :: 3.3
Requires-Dist: daterange (==0.3)
Requires-Dist: icalendar
Requires-Dist: lxml
Requires-Dist: requests
